cli_select/__init__.py
cli_select/helper.py
cli_select-0.0.4.dist-info/METADATA
cli_select-0.0.4.dist-info/WHEEL
cli_select-0.0.4.dist-info/licenses/LICENSE
cli_select-0.0.4.dist-info/RECORD
